cerl/__init__.py
cerl/cerl.py
cerl/utils.py
cerl-0.0.5.dist-info/METADATA
cerl-0.0.5.dist-info/WHEEL
cerl-0.0.5.dist-info/top_level.txt
cerl-0.0.5.dist-info/RECORD
