Metadata-Version: 2.1
Name: cerl
Version: 0.0.5
Summary: Library for querying CERL infrastructure
Home-page: UNKNOWN
Author: Andreas Walker
Author-email: walker@sub.uni-goettingen.de
License: MIT
Platform: UNKNOWN
Classifier: Programming Language :: Python :: 3
Requires-Python: >=3.8.5
Requires-Dist: requests
